{"model_id": "music_v1", "composition_plan": {"positive_global_styles": ["dark gospel blues soul with cinematic orchestral weight", "Steinway grand piano driven", "raw emotion", "D minor", "74 BPM", "voice-first production with cinematic and gospel influences", "call and response between raspy soulful male tenor and female blues alto", "spiritual weight", "harmony not unison on duet sections", "male voice mid-range tenor raspy with raw soul power and ache", "male vocals higher register with grit that soars and cracks with feeling", "female voice deep blues alto warm and ancient like Nina Simone", "cinematic builds from whisper to cathedral", "staccato upper register piano motif throughout like amber pulses of light", "dramatic tension and release", "epic and intimate at the same time"], "negative_global_styles": ["pop", "electronic", "bright", "upbeat", "synthetic", "auto-tune", "overproduced", "busy arrangement", "drum machine", "clean polished vocals", "smooth male vocals", "deep bass male voice", "baritone", "generic", "happy"], "sections": [{"section_name": "Instrumental Intro", "positive_local_styles": ["solo Steinway grand piano", "low D minor sustained chord", "staccato upper register piano notes scattered like flickering light", "single female vocal hum enters warm and sustained", "dark atmospheric", "cinematic tension building", "sparse cold beautiful", "reverb heavy room", "dramatic cinematic intro energy"], "negative_local_styles": ["drums", "bass", "organ", "saxophone", "bright", "fast", "lyrics", "words"], "duration_ms": 15000, "lines": []}, {"section_name": "Spoken Intro", "positive_local_styles": ["whispered spoken word over piano", "reverb heavy", "staccato piano dims to single notes", "two voices in darkness", "intimate and haunting", "cinematic spoken opening"], "negative_local_styles": ["singing", "drums", "bass", "organ", "bright", "energetic"], "duration_ms": 8000, "lines": ["A dead man wrote it down so we wouldn't forget", "Two thousand years and the dust still hasn't settled"]}, {"section_name": "Verse 1", "positive_local_styles": ["slow gospel blues piano pattern", "finger snaps on 2 and 4", "staccato upper piano notes flutter at phrase endings", "raspy male tenor raw and aching half talking half singing", "female blues alto answers sharp and grounded", "call and response", "intimate and conversational", "voice first piano supports never leads", "building slowly toward power"], "negative_local_styles": ["full arrangement", "drums", "organ", "energetic", "loud"], "duration_ms": 45000, "lines": ["We built this thing with splinters in our palms", "No map no mercy", "Just sawdust on the floor", "And climbed the shelves to escape the fight", "Watched it close in while we were trapped inside", "And found our wisdom in the meditations", "Started from the dust again", "Blindfolded if we had to", "Some of us don't talk about the fire we just swipe right by", "Some lessons don't knock baby", "They kick the door in", "It ain't the fire it's who stayed when the air ran out", "The only thing we ever really own", "Is the love we keep fighting for"]}, {"section_name": "Pre-Chorus 1", "positive_local_styles": ["building intensity", "piano chords opening up wider", "organ fades in underneath on last lines only", "staccato amber motif steadies into rhythm", "male and female call and response rising", "gospel build toward chorus", "cinematic swell beginning"], "negative_local_styles": ["full drums", "saxophone", "sparse", "quiet"], "duration_ms": 18000, "lines": ["We can't tell the sky what to do with its rain", "Can't hold back the flood", "Or put these broken walls up again", "No we never could", "But we can lay every stone down where it matters most", "That's the only thing that doesn't rot", "The only kingdom that's complete"]}, {"section_name": "Chorus 1", "positive_local_styles": ["powerful gospel blues chorus", "organ swells in", "piano pounds deep chords", "staccato motif moves in harmonic intervals minor thirds and sixths", "male and female vocals in rich harmony", "spiritual and heavy", "congregation energy", "raw and powerful", "dramatic cinematic chorus energy epic but earned", "cinematic and sweeping"], "negative_local_styles": ["sparse", "quiet", "spoken", "drums", "saxophone", "restrained"], "duration_ms": 25000, "lines": ["We're all just sawdust in the end", "What you build will break what breaks you build again", "Why you gripping walls you never shaped", "Let it go let it fall", "There's sawdust at your feet", "We're all just sawdust in the end", "But God not tonight", "We're gonna build again"]}, {"section_name": "Post-Chorus Breath", "positive_local_styles": ["instrumental interlude", "piano climbing slowly", "staccato amber motif scattered and flickering", "voices humming underneath no words", "spacious and breathing", "letting the chorus settle", "cinematic breathing room"], "negative_local_styles": ["drums", "saxophone", "loud", "fast", "lyrics", "words"], "duration_ms": 15000, "lines": []}, {"section_name": "Verse 2", "positive_local_styles": ["intimate gospel blues", "piano only", "staccato motif sparse and dim single amber notes far apart", "male tenor vocals intimate and vulnerable", "female blues alto stronger now the anchor", "subtle brush on snare rim", "contemplative", "call and response", "darker than verse 1"], "negative_local_styles": ["full arrangement", "organ", "drums", "energetic", "loud"], "duration_ms": 40000, "lines": ["They'll crown anything that shines long enough", "Bow to kings who turn to bones", "Before the century has passed", "Every single one of them", "Every name they hammered into marble", "Just someone who built a kingdom cold", "And died reaching for a hand to hold", "So why we spending all this time building walls alone", "We chose being right over being here", "And the house is cold when we get home", "Every single time", "That mountain they put in our path", "Child that was the path", "And the only life that dies too soon is the one no one touched"]}, {"section_name": "Pre-Chorus 2", "positive_local_styles": ["building intensity heavier than first pre-chorus", "organ returning fuller", "bass note pedal underneath", "staccato motif returns steadier like a pulse strengthening", "gospel build with weight", "male and female call and response with conviction", "cinematic crescendo building"], "negative_local_styles": ["sparse", "saxophone", "quiet", "restrained"], "duration_ms": 18000, "lines": ["We can't fix the world or all the noise inside our heads", "Can't undo the years we lost", "Running from the ones who stayed", "No that's gone now", "But we can show up with our hands open", "Lay it down lay it all down", "And build it around the ones who stayed"]}, {"section_name": "Chorus 2", "positive_local_styles": ["powerful gospel blues chorus heavier than first", "organ louder", "male and female tight harmony with more conviction", "staccato motif more insistent amber pulses closer together", "building toward something massive", "cinematic power"], "negative_local_styles": ["sparse", "quiet", "drums", "saxophone", "restrained"], "duration_ms": 25000, "lines": ["We're all just sawdust in the end", "What you build will break what breaks you build again", "Why you gripping walls you never shaped", "Let it go let it fall", "There's sawdust at your feet", "We're all just sawdust in the end", "But God not tonight", "We're gonna build again"]}, {"section_name": "Bridge", "positive_local_styles": ["everything stripped to nothing", "just low D pulse like heartbeat in dark room", "no sustain pedal", "staccato motif completely gone darkness", "male vocals almost whispered navigating in the dark", "female vocals sharp then soft and close", "piano drops out completely for one line total silence", "male voice gasps single breath coming back to air", "piano re-enters higher register amber light returning", "saxophone enters low and mournful midway", "builds to three part harmony stack", "organ swells underneath at end", "cinematic tension and release like a film score", "the most intimate and devastating section", "confession in an empty church"], "negative_local_styles": ["drums", "energetic", "fast", "loud at start", "full arrangement at start"], "duration_ms": 50000, "lines": ["Some of us lost our legs before we learned to stand", "And still they told us run", "We carry marks in places no one thinks to look", "Wood and dark and shapes with no name", "Felt the grain against our skin the dust of something built before us", "The rhythm they left in our bones", "We found the door by feel alone", "Set the glass down watched the world steady itself", "We were shaking not the room", "We thought the kingdom was the walls we built", "Turns out it was you", "We spent our whole lives digging outward", "When the well was always within", "No house survives on one pair of hands", "And when the walls fell in", "Someone was still inside", "Holding the weight", "Amen"]}, {"section_name": "Final Chorus", "positive_local_styles": ["enters soft voices and piano only then builds to massive", "staccato amber motif returns rapid the room full of light", "floor tom heartbeat enters then full drum kit halfway", "organ and saxophone join and swell", "roles reverse female leads male responds", "both voices at full power by the end", "massive gospel climax cathedral energy", "dramatic cinematic final chorus energy cinematic and overwhelming", "D minor building to resolution", "epic and earned not cheap", "the amber motif is everywhere the pulse that kept coming back"], "negative_local_styles": ["restrained at end", "quiet at end", "sparse at end"], "duration_ms": 28000, "lines": ["We're all just sawdust in the end", "What you build will break what breaks you build again", "Why you gripping walls you never shaped", "Let it go let it fall", "There's sawdust at your feet", "Sawdust in the end but while we're here", "Stand beside the ones we love and finally see clear", "We built it once and life reduced it all to ash", "We'll lay the stone again", "We always do"]}, {"section_name": "Outro", "positive_local_styles": ["everything fades to piano alone", "same D minor chord from intro full circle", "staccato amber motif returns sparse single notes flickering", "female vocal hum returns same as intro", "spoken male voice over last piano chord", "whispered female response barely there", "final piano note rings out and decays into nothing", "long silence", "haunting and final", "cinematic ending"], "negative_local_styles": ["drums", "organ", "saxophone", "energetic", "loud", "fast"], "duration_ms": 13000, "lines": ["All this for a pile of dust", "But look what you built"]}]}, "enforce_section_duration": false, "with_timestamps": true}